{"body":{"coverUri":"https://2022.npp.vote/api/v1/attachment/1197","type":"CITIZEN_REPRESENTATIVE","status":"UNCURRENT","id":69,"name":"王南昕","electorate":"澎湖縣馬公市第二選區<br>西衛、重光、朝陽、陽明、光復、光明、光榮","weight":1,"contact":"聯絡我們","support":"支持我們","politics":"政策","declaration":"共享創新．服務用昕","areaId":27,"areaName":"澎湖縣","createdAt":"2022-09-07T04:07:02.402Z","candidateAttachments":[],"candidateContacts":[{"id":1017,"title":"電話","content":"0932-714-597","createdAt":"2022-09-07T04:07:03.078Z"}],"candidateDeclaration":{"id":1002,"title":"打造澎湖為成家立業的島嶼","content":"<p>十年前來到澎湖，我用慢跑和浮潛探索自我，也認識這片多樣的島與海，柔軟的樹、寬廣的海，接納我、也讓我充飽能量。我曾全職投入博弈公投的反賭運動，不是單單為了反對什麼，而是為了建設更美好的澎湖。</p>\n<p>&nbsp;</p>\n<p>這些年，有越來越多年輕人，用心在澎湖扎根發展，滾動了正向的連鎖反應。但兩大黨縣長提名還是固定老面孔，一再歹戲拖棚。</p>\n<p>感謝一千多位獨立公民，在四年前投給我，展現求新求變的願望。我認為，民意代表不只做到「燈亮、路平、水溝通」，更要做到「共享創新．服務用昕」。</p>\n<p>&nbsp;</p>\n<p>大家辛苦繳交的稅金，不該亂蓋蚊子館，像花火節的煙火稍縱即逝，反反覆覆弄壞我們的海洋和土地。如果改用一點點預算來做創新，從政府做起，改用可重複使用的餐具，推動共享杯，從源頭減少垃圾，點滴邁向零廢棄的乾淨島嶼。經費不用太多，就能建設U-bike公共自行車系統、共享機車，和進入狹窄巷弄的社區小巴。</p>\n<p>&nbsp;</p>\n<p>各領域的專家，他們都很樂意一起來實踐創新。海膽才開放採捕就沒了，而水產養殖專家正在加速人工養殖的試驗。我支持《海洋保育法》的立法，縣府應該創新海洋和漁業管理，大幅添補海洋研究與執法的人力，各種魚源更豐盛，讓後代子孫都有魚可以吃。</p>\n<p>&nbsp;</p>\n<p>我希望這美麗的神秘島嶼，不只是外地年輕人畢業旅行的回憶，更要吸引各地年輕人來這裡成家立業，有健康的生活、快樂的心情，和尊嚴的工作。</p>\n<p>&nbsp;</p>","createdAt":"2022-09-07T04:07:02.983Z"},"candidateEducations":[{"id":1044,"title":"台師大 永續管理與環境教育所研究生","content":null,"weight":2,"createdAt":"2022-09-07T04:07:03.266Z"},{"id":1043,"title":"澎科大 應用外語系畢業 ","content":null,"weight":1,"createdAt":"2022-09-07T04:07:02.990Z"}],"candidateExperiences":[{"id":1122,"title":"哲學與社會民主工作室教育專員","content":null,"weight":5,"createdAt":"2022-09-07T04:07:03.074Z"},{"id":1123,"title":"澎科大行銷物流暨服務業管理所研究助理","content":null,"weight":4,"createdAt":"2022-09-07T04:07:03.279Z"},{"id":1124,"title":"澎湖縣反賭場聯盟前主任秘書","content":null,"weight":3,"createdAt":"2022-09-07T04:07:03.712Z"},{"id":1125,"title":"弱勢學生課輔教師","content":null,"weight":2,"createdAt":"2022-09-07T04:07:03.895Z"},{"id":1126,"title":"浮潛教練、海洋生態導覽員、獨立長笛演奏者、長照居服員","content":null,"weight":1,"createdAt":"2022-09-07T04:07:04.064Z"}],"candidatePolitics":[{"id":1110,"title":"囝仔教育足輕鬆","content":"優質－發展多元學習。\n敢生－公托公幼名額多三倍","weight":100,"createdAt":"2022-09-07T04:07:03.883Z"},{"id":1107,"title":"多語世界觀光島","content":"輔導製作多語菜單，贏得國際觀光財","weight":100,"createdAt":"2022-09-07T04:07:03.063Z"},{"id":1108,"title":"在地文化來企起","content":"規劃文化步道。推動社宅讓青年住得起","weight":100,"createdAt":"2022-09-07T04:07:03.276Z"},{"id":1109,"title":"便利交通好停車","content":"推動Ubike、共享機車、社區小巴，人本交通低碳島","weight":100,"createdAt":"2022-09-07T04:07:03.710Z"},{"id":1111,"title":"海洋公民有未來","content":"親海－人人都學會游泳。護海－讓子孫還有魚可吃。","weight":100,"createdAt":"2022-09-07T04:07:04.057Z"}],"candidateSocial":{"id":1000,"line":null,"facebook":null,"email":"ycnan52315@gmail.com","instagram":null,"youtube":null,"createdAt":"2022-09-07T04:07:02.975Z"},"candidateSupports":[{"id":1031,"title":"看板和志工應援","content":null,"weight":2,"createdAt":"2022-09-07T04:07:03.270Z"},{"id":1030,"title":"政治獻金專戶","content":null,"weight":1,"createdAt":"2022-09-07T04:07:03.068Z"}]}}